couchdbauthenticator/__init__.py
couchdbauthenticator/authenticator.py
couchdbauthenticator/metadata.py
couchdbauthenticator/user_manager.py
jupyterhub_couchdb_authenticator-0.6.dist-info/LICENSE
jupyterhub_couchdb_authenticator-0.6.dist-info/METADATA
jupyterhub_couchdb_authenticator-0.6.dist-info/WHEEL
jupyterhub_couchdb_authenticator-0.6.dist-info/top_level.txt
jupyterhub_couchdb_authenticator-0.6.dist-info/RECORD
