Metadata-Version: 2.1
Name: jupyterhub-couchdb-authenticator
Version: 0.6
Summary: Couchdb Authenticator for JupyterHub
Home-page: https://github.com/1kastner/CouchDBAuthenticator
Author: Marvin Kastner
Author-email: marvin.kastner@tuhh.de
License: MIT
Platform: UNKNOWN
License-File: LICENSE
Requires-Dist: requests
Requires-Dist: jupyterhub
Requires-Dist: tornado
Requires-Dist: traitlets
Provides-Extra: dev
Requires-Dist: flake8 ; extra == 'dev'
Requires-Dist: pylint ; extra == 'dev'
Requires-Dist: twine ; extra == 'dev'
Provides-Extra: example
Requires-Dist: python-dotenv ; extra == 'example'
